HDEd25519_nacl/__init__.py
HDEd25519_nacl/py.typed
HDEd25519-0.0.2.dist-info/LICENSE
HDEd25519-0.0.2.dist-info/METADATA
HDEd25519-0.0.2.dist-info/WHEEL
HDEd25519-0.0.2.dist-info/top_level.txt
HDEd25519-0.0.2.dist-info/RECORD
