Metadata-Version: 2.1
Name: HDEd25519
Version: 0.0.2
Summary: HDEd25519 derivation used by Ledger products
Home-page: https://github.com/LedgerHQ/HDEd25519
Author: Ledger
Author-email: hello@ledger.com
License: UNKNOWN
Platform: UNKNOWN
Classifier: Programming Language :: Python :: 3
Classifier: License :: OSI Approved :: MIT License
Classifier: Operating System :: OS Independent
License-File: LICENSE
Requires-Dist: pynacl (>=1.4.0)
